README.rst
setup.py
scrapy_jsonrpc/__init__.py
scrapy_jsonrpc/jsonrpc.py
scrapy_jsonrpc/serialize.py
scrapy_jsonrpc/txweb.py
scrapy_jsonrpc/webservice.py
scrapy_jsonrpc_api_py3.egg-info/PKG-INFO
scrapy_jsonrpc_api_py3.egg-info/SOURCES.txt
scrapy_jsonrpc_api_py3.egg-info/dependency_links.txt
scrapy_jsonrpc_api_py3.egg-info/not-zip-safe
scrapy_jsonrpc_api_py3.egg-info/requires.txt
scrapy_jsonrpc_api_py3.egg-info/top_level.txt