Metadata-Version: 2.1
Name: scrapy-jsonrpc-api-py3
Version: 1.0.2
Summary: Scrapy extenstion to control spiders using JSON-RPC By songhao8080
Home-page: https://github.com/songhao8080/scrapy-jsonrpc
Author: Scrapy developers,songhao8080
License: BSD
Platform: UNKNOWN
Classifier: Framework :: Scrapy
Classifier: Development Status :: 4 - Beta
Classifier: Environment :: Console
Classifier: Intended Audience :: Developers
Classifier: License :: OSI Approved :: BSD License
Classifier: Operating System :: OS Independent
Classifier: Programming Language :: Python
Classifier: Programming Language :: Python :: 2
Classifier: Programming Language :: Python :: 3.6
Classifier: Programming Language :: Python :: 3.8
Classifier: Topic :: Internet :: WWW/HTTP
